.env
.gitignore
LICENSE
MANIFEST.in
README.md
dev-requirements.txt
setup.py
debian/.gitignore
debian/changelog
debian/compat
debian/control
debian/copyright
debian/postinst
debian/postrm
debian/preinst
debian/prerm
debian/rules
debian/sentry.io.dirs
debian/sentry.io.install
debian/sentry.io.links
debian/sentry.io.triggers
debian/source/options
debianized_sentry.egg-info/PKG-INFO
debianized_sentry.egg-info/SOURCES.txt
debianized_sentry.egg-info/dependency_links.txt
debianized_sentry.egg-info/requires.txt
debianized_sentry.egg-info/top_level.txt
etc/config.yml
etc/sentry.conf.py
etc/cron.d/sentry
etc/default/sentry
scripts/sentry-cron
scripts/sentry-web
scripts/sentry-worker
systemd/sentry-cron.service
systemd/sentry-web.service
systemd/sentry-worker.service