Metadata-Version: 1.1
Name: debianized-sentry
Version: 8.22.0.2
Summary: Debian packaging for Sentry, a modern realtime error logging and aggregation platform.
Home-page: https://github.com/1and1/debianized-sentry#sentryio-debian-packaging
Author: Juergen Hermann
Author-email: jh@web.de
License: BSD 3-clause
Keywords: debian-packages,dh-virtualenv,sentry,deployment,devops,omnibus-packages
Platform: UNKNOWN
Classifier: Development Status :: 5 - Production/Stable
Classifier: Environment :: Web Environment
Classifier: Framework :: Django
Classifier: Intended Audience :: Developers
Classifier: Intended Audience :: Information Technology
Classifier: Intended Audience :: System Administrators
Classifier: License :: OSI Approved :: BSD License
Classifier: Operating System :: POSIX :: Linux
Classifier: Programming Language :: Python :: 2.7
Classifier: Topic :: System :: Monitoring
Classifier: Topic :: System :: Logging
